lifecyclestatebroadcastsdk/__init__.py
lifecyclestatebroadcastsdk/targetsettingsfileparser.py
lifecyclestatebroadcastsdk/targetsettingsfilereader.py
lifecyclestatebroadcastsdk/templates/default.j2
lifecycle_state_broadcast_sdk-1.0.1.dist-info/LICENSE
lifecycle_state_broadcast_sdk-1.0.1.dist-info/METADATA
lifecycle_state_broadcast_sdk-1.0.1.dist-info/WHEEL
lifecycle_state_broadcast_sdk-1.0.1.dist-info/top_level.txt
lifecycle_state_broadcast_sdk-1.0.1.dist-info/RECORD
